pycewl/__init__.py
pycewl/__main__.py
pycewl/cli.py
pycewl/config.py
pycewl/extractors/__init__.py
pycewl/extractors/emails.py
pycewl/extractors/metadata.py
pycewl/extractors/words.py
pycewl/google/__init__.py
pycewl/google/nlp.py
pycewl/google/search.py
pycewl/http/__init__.py
pycewl/http/auth.py
pycewl/http/client.py
pycewl/output/__init__.py
pycewl/output/writers.py
pycewl/spider/__init__.py
pycewl/spider/crawler.py
pycewl/spider/filters.py
pycewl/spider/url_manager.py
pycewl-0.1.0.dist-info/METADATA
pycewl-0.1.0.dist-info/WHEEL
pycewl-0.1.0.dist-info/entry_points.txt
pycewl-0.1.0.dist-info/RECORD
