Metadata-Version: 2.4
Name: pycewl
Version: 0.1.0
Summary: Python async re-implementation of CeWL (Custom Word List Generator)
Project-URL: Homepage, https://github.com/digininja/CeWL
Project-URL: Documentation, https://github.com/digininja/CeWL
Project-URL: Repository, https://github.com/digininja/CeWL
Author-email: James <james@example.com>
License-Expression: MIT
Keywords: crawler,pentesting,security,spider,wordlist
Classifier: Development Status :: 4 - Beta
Classifier: Environment :: Console
Classifier: Intended Audience :: Developers
Classifier: Intended Audience :: Information Technology
Classifier: License :: OSI Approved :: MIT License
Classifier: Operating System :: OS Independent
Classifier: Programming Language :: Python :: 3
Classifier: Programming Language :: Python :: 3.11
Classifier: Programming Language :: Python :: 3.12
Classifier: Topic :: Internet :: WWW/HTTP :: Indexing/Search
Classifier: Topic :: Security
Classifier: Typing :: Typed
Requires-Python: >=3.11
Requires-Dist: beautifulsoup4>=4.12.0
Requires-Dist: google-cloud-language>=2.13.0
Requires-Dist: httpx>=0.27.0
Requires-Dist: lxml>=5.0.0
Requires-Dist: rich>=13.7.0
Requires-Dist: typer>=0.12.0
Provides-Extra: all
Requires-Dist: mkdocs-material>=9.5.0; extra == 'all'
Requires-Dist: mkdocs>=1.5.0; extra == 'all'
Requires-Dist: mypy>=1.9.0; extra == 'all'
Requires-Dist: pypdf>=4.0.0; extra == 'all'
Requires-Dist: pytest-asyncio>=0.23.0; extra == 'all'
Requires-Dist: pytest-httpx>=0.30.0; extra == 'all'
Requires-Dist: pytest>=8.0.0; extra == 'all'
Requires-Dist: ruff>=0.3.0; extra == 'all'
Requires-Dist: types-beautifulsoup4>=4.12.0; extra == 'all'
Provides-Extra: dev
Requires-Dist: mypy>=1.9.0; extra == 'dev'
Requires-Dist: pytest-asyncio>=0.23.0; extra == 'dev'
Requires-Dist: pytest-httpx>=0.30.0; extra == 'dev'
Requires-Dist: pytest>=8.0.0; extra == 'dev'
Requires-Dist: ruff>=0.3.0; extra == 'dev'
Requires-Dist: types-beautifulsoup4>=4.12.0; extra == 'dev'
Provides-Extra: docs
Requires-Dist: mkdocs-material>=9.5.0; extra == 'docs'
Requires-Dist: mkdocs>=1.5.0; extra == 'docs'
Provides-Extra: pdf
Requires-Dist: pypdf>=4.0.0; extra == 'pdf'
